{"meta":{"id":"dubanime_7358","kitsu_id":"7358","type":"series","animeType":"TV","name":"Kamisama no Inai Nichiyoubi","slug":"kamisama-no-inai-nichiyoubi","aliases":["Sunday Without God","Kamisama no Inai Nichiyoubi","The Sunday Without God","Kami-Nai","Kami-sama no Inai Nichiyoubi"],"genres":["Mystery","Fantasy"],"poster":"https://media.kitsu.io/anime/poster_images/7358/small.jpg?1408461081","background":"https://media.kitsu.io/anime/cover_images/7358/original.jpg?1519183403","description":"God has abandoned the world. As a result, life cannot end nor can new life be born, and the \"dead\" walk restlessly among the living. Granting one last miracle before turning away forever, God created \"gravekeepers,\" mystical beings capable of putting the dead to rest through a proper burial. Ai Astin, a cheerful but naïve young girl, serves as her village's gravekeeper in place of her late mother.\r\nOne day, a man known as Hampnie Hambart, who is supposedly Ai's father, arrives and kills all the people in her village. Having lost her village and with no plans for the future, Ai decides to accompany the mysterious man on his journey. As she travels the land, the young gravekeeper strives to fulfill her duties, granting peace to the dead and assisting the living, while at the same time learning more about the world that God left in this tragic state.\r\n[Written by MAL Rewrite]","releaseInfo":"2013","year":"2013","imdbRating":7.212999999999999,"userCount":17870,"status":"finished","runtime":"23 min","trailers":[{"source":"nIYJXpaxO7M","type":"Trailer"}],"videos":[{"id":"dubanime_7358:1","title":"Valley of Death I","released":"2013-07-07T00:00:00.001Z","season":1,"episode":1,"imdb_id":"tt2904550","imdbSeason":1,"imdbEpisode":1},{"id":"dubanime_7358:2","title":"Valley of Death II","released":"2013-07-07T00:00:00.002Z","season":1,"episode":2,"imdb_id":"tt2904550","imdbSeason":1,"imdbEpisode":2},{"id":"dubanime_7358:3","title":"Valley of Death III","released":"2013-07-07T00:00:00.003Z","season":1,"episode":3,"imdb_id":"tt2904550","imdbSeason":1,"imdbEpisode":3},{"id":"dubanime_7358:4","title":"Ortus I","released":"2013-07-07T00:00:00.004Z","season":1,"episode":4,"imdb_id":"tt2904550","imdbSeason":1,"imdbEpisode":4},{"id":"dubanime_7358:5","title":"Ortus II","released":"2013-07-07T00:00:00.005Z","season":1,"episode":5,"imdb_id":"tt2904550","imdbSeason":1,"imdbEpisode":5},{"id":"dubanime_7358:6","title":"Ortus III","released":"2013-07-07T00:00:00.006Z","season":1,"episode":6,"imdb_id":"tt2904550","imdbSeason":1,"imdbEpisode":6},{"id":"dubanime_7358:7","title":"Goran Academy I","released":"2013-07-07T00:00:00.007Z","season":1,"episode":7,"imdb_id":"tt2904550","imdbSeason":1,"imdbEpisode":7},{"id":"dubanime_7358:8","title":"Goran Academy II","released":"2013-07-07T00:00:00.008Z","season":1,"episode":8,"imdb_id":"tt2904550","imdbSeason":1,"imdbEpisode":8},{"id":"dubanime_7358:9","title":"Where Gravekeepers are Born","released":"2013-07-07T00:00:00.009Z","season":1,"episode":9,"imdb_id":"tt2904550","imdbSeason":1,"imdbEpisode":9},{"id":"dubanime_7358:10","title":"Class 3-4 I","released":"2013-07-07T00:00:00.010Z","season":1,"episode":10,"imdb_id":"tt2904550","imdbSeason":1,"imdbEpisode":10},{"id":"dubanime_7358:11","title":"Class 3-4 II","released":"2013-07-07T00:00:00.011Z","season":1,"episode":11,"imdb_id":"tt2904550","imdbSeason":1,"imdbEpisode":11},{"id":"dubanime_7358:12","title":"Class 3-4 III","released":"2013-07-07T00:00:00.012Z","season":1,"episode":12,"imdb_id":"tt2904550","imdbSeason":1,"imdbEpisode":12}],"imdb_id":"tt2904550"},"cacheMaxAge":4320}